pystran/__init__.py
pystran/assemble.py
pystran/beam.py
pystran/freedoms.py
pystran/gauss.py
pystran/geometry.py
pystran/model.py
pystran/plots.py
pystran/rigid.py
pystran/rotation.py
pystran/section.py
pystran/spring.py
pystran/truss.py
pystran-0.0.2.dist-info/METADATA
pystran-0.0.2.dist-info/WHEEL
pystran-0.0.2.dist-info/licenses/LICENSE
pystran-0.0.2.dist-info/RECORD
