Metadata-Version: 2.4
Name: pystran
Version: 0.0.2
Summary: Python Structural Analysis package
Project-URL: Homepage, https://github.com/PetrKryslUCSD/pystran
Project-URL: Issues, https://github.com/PetrKryslUCSD/pystran/issues
Author-email: Petr Krysl <pkrysl@ucsd.edu>
License-Expression: MIT
License-File: LICENSE
Classifier: Operating System :: OS Independent
Classifier: Programming Language :: Python :: 3
Requires-Python: >=3.9
